Metadata-Version: 2.1
Name: dgbg
Version: 0.0.2
Summary: Docking grid box generator for Autodock4 and Vina
Home-page: UNKNOWN
Author: Usman Jamshed
Author-email: jamshedu@berkeley.edu
License: MIT
Download-URL: https://github.com/ujamshed/dgbg/archive/refs/tags/0.0.2.tar.gz
Keywords: core package
Platform: UNKNOWN
Classifier: Development Status :: 5 - Production/Stable
Classifier: License :: OSI Approved :: MIT License
Classifier: Programming Language :: Python :: 3
Classifier: Operating System :: OS Independent
License-File: LICENSE
